gridpp.py
_gridpp.so
gridpp-0.7.1.dist-info/top_level.txt
gridpp-0.7.1.dist-info/METADATA
gridpp-0.7.1.dist-info/WHEEL
gridpp-0.7.1.dist-info/RECORD
gridpp.libs/libblas-2d5b9174.so.3.0.3
gridpp.libs/libarmadillo-d3a49b0e.so.6.500.5
gridpp.libs/libsuperlu-58f4b21a.so.4.3
gridpp.libs/libcblas-de16e930.so.3.0
gridpp.libs/libatlas-dd66cbe8.so.3.0
gridpp.libs/libgomp-3300acd3.so.1.0.0
gridpp.libs/libgfortran-bfa58d52.so.1.0.0
gridpp.libs/libf77blas-60dfc405.so.3.0
gridpp.libs/liblapack-794335ae.so.3.0
gridpp.libs/libarpack-828458d7.so.2.0.0
